Metadata-Version: 1.0
Name: htp-client
Version: 0.5.3
Summary: Make a Hecks engine using the HTP protocol play on the hecks.space website
Home-page: http://github.com/unc0mm0n/htp-client.git
Author: Yuval Wyborski
Author-email: yvw.bor@gmail.com
License: WTFPL
Platform: UNKNOWN
